LICENSE
MANIFEST.in
README.md
setup.py
osbuilder/__init__.py
osbuilder.egg-info/PKG-INFO
osbuilder.egg-info/SOURCES.txt
osbuilder.egg-info/dependency_links.txt
osbuilder.egg-info/requires.txt
osbuilder.egg-info/top_level.txt
osbuilder/__pycache__/__init__.cpython-39.pyc
osbuilder/postprocess/__init__.py
osbuilder/postprocess/opensees_to_gid/__init__.py
osbuilder/postprocess/opensees_to_gid/element_result.pyc
osbuilder/postprocess/opensees_to_gid/gauss_point.pyc
osbuilder/postprocess/opensees_to_gid/get_model_info.pyc
osbuilder/postprocess/opensees_to_gid/head.pyc
osbuilder/postprocess/opensees_to_gid/node_result.pyc
osbuilder/postprocess/opensees_to_gid/result_on_gausspoint.pyc
osbuilder/postprocess/opensees_to_gid/result_on_node.pyc
osbuilder/preprocess/__init__.py
osbuilder/preprocess/__pycache__/__init__.cpython-39.pyc
osbuilder/preprocess/abaqus_to_opensees/__init__.py
osbuilder/preprocess/abaqus_to_opensees/get_model_info.pyc
osbuilder/preprocess/abaqus_to_opensees/__pycache__/__init__.cpython-39.pyc
osbuilder/preprocess/abaqus_to_opensees/__pycache__/get_model_info.cpython-39.pyc
osbuilder/preprocess/boundary/__init__.py
osbuilder/preprocess/boundary/general.pyc
osbuilder/preprocess/boundary/multi_transmision_boundary.pyc
osbuilder/preprocess/boundary/shear_boundary.pyc
osbuilder/preprocess/boundary/tools.pyc
osbuilder/preprocess/boundary/vsb.pyc
osbuilder/preprocess/boundary/__pycache__/__init__.cpython-39.pyc
osbuilder/preprocess/boundary/__pycache__/general.cpython-39.pyc
osbuilder/preprocess/boundary/__pycache__/multi_transmision_boundary.cpython-39.pyc
osbuilder/preprocess/boundary/__pycache__/shear_boundary.cpython-39.pyc
osbuilder/preprocess/boundary/__pycache__/vsb.cpython-39.pyc
osbuilder/preprocess/load/__init__.py
osbuilder/preprocess/load/amplitude.pyc
osbuilder/preprocess/load/lamb.pyc
osbuilder/preprocess/load/load.pyc
osbuilder/preprocess/load/recorder.pyc
osbuilder/preprocess/load/step.pyc
osbuilder/preprocess/load/tools.pyc
osbuilder/preprocess/part/OpenSeesVisPyvista.pyc
osbuilder/preprocess/part/__init__.py
osbuilder/preprocess/part/beam_profile.pyc
osbuilder/preprocess/part/constraint.pyc
