Metadata-Version: 2.1
Name: osbuilder
Version: 3.2.1.1
Summary: The pre-& post-processing for openseespy.
Author: zarhin
Author-email: lizaixianvip@live.com
License-File: LICENSE
